{
    "failures": [
        {
            "pushButtonState": true,
            "hob3HeatLevelSetting": 90,
            "standby": false,
            "latitude": -62.02728862085637,
            "batteryChargingState": true,
            "lockBit": true,
            "powerUsageEstimate": 3558.5,
            "deviceStatus": "Driver Not Ready",
            "hob2HeatLevelRemaining": 79,
            "apiUrl": "GTVA6orVf0",
            "hob4HeatLevelSetting": 10,
            "repeaterRssi": -52.7,
            "supportedCommunicationIntervals": "KZZ0AOUQDJ",
            "batteryLevel": 79.113,
            "longitude": 31.63486925592528,
            "on": false,
            "communicationInterval": 81910,
            "rssi": -81.2,
            "batteryVoltage": 6.77,
            "powerUsage": 1424.2,
            "declaredMaximumPower": 1846,
            "hob3HeatLevelRemaining": 61,
            "voltage": 808146.552,
            "connectionStatus": true,
            "gatewayIdentifier": "DHUd7W4PaW",
            "hob1HeatLevelRemaining": 96,
            "hob4HeatLevelRemaining": 34,
            "configuredLocationName": "tFCGnjoaMf",
            "hob2HeatLevelSetting": 10
        },
        {
            "pushButtonState": false,
            "hob3HeatLevelSetting": 30,
            "standby": false,
            "latitude": -60.35088777445061,
            "batteryChargingState": false,
            "lockBit": true,
            "powerUsageEstimate": 3230.3,
            "deviceStatus": "OK",
            "hob1HeatLevelSetting": 80,
            "hob2HeatLevelRemaining": 61,
            "apiUrl": "TgZvtwMTPV",
            "hob4HeatLevelSetting": 80,
            "repeaterRssi": -122.7,
            "supportedCommunicationIntervals": "ehU3GCNQsy",
            "batteryLevel": 84.813,
            "longitude": -1.5939899053140039,
            "on": false,
            "communicationInterval": 67563,
            "rssi": -1.4,
            "batteryVoltage": 7.85,
            "powerUsage": 2621.8,
            "declaredMaximumPower": 157.8,
            "hob3HeatLevelRemaining": 84,
            "voltage": 372647.685,
            "connectionStatus": false,
            "gatewayIdentifier": "yOYwgb1Sol",
            "hob1HeatLevelRemaining": 84,
            "hob4HeatLevelRemaining": 7,
            "configuredLocationName": "weLUHxzzLS"
        },
        {
            "pushButtonState": false,
            "standby": true,
            "latitude": 87.39388199255492,
            "batteryChargingState": false,
            "lockBit": false,
            "powerUsageEstimate": 2896.8,
            "deviceStatus": "Driver Stopped",
            "hob1HeatLevelSetting": 40,
            "hob2HeatLevelRemaining": 81,
            "apiUrl": "Jw0yOIiE7t",
            "hob4HeatLevelSetting": 80,
            "repeaterRssi": -23.4,
            "supportedCommunicationIntervals": "rBNnfNF377",
            "batteryLevel": 20.209,
            "longitude": -127.01460486358701,
            "on": true,
            "communicationInterval": 70612,
            "rssi": -119.8,
            "batteryVoltage": 6.28,
            "powerUsage": 3427.4,
            "declaredMaximumPower": 390.8,
            "hob3HeatLevelRemaining": 83,
            "voltage": -334876.772,
            "connectionStatus": false,
            "gatewayIdentifier": "QIwc57tB1Z",
            "hob1HeatLevelRemaining": 52,
            "hob4HeatLevelRemaining": 85,
            "configuredLocationName": "i8xZn8x5Iz",
            "hob2HeatLevelSetting": 40
        },
        {
            "pushButtonState": false,
            "hob3HeatLevelSetting": 90,
            "standby": true,
            "latitude": 49.48877776695184,
            "batteryChargingState": true,
            "lockBit": false,
            "powerUsageEstimate": 324.1,
            "deviceStatus": "OK",
            "hob1HeatLevelSetting": 80,
            "hob2HeatLevelRemaining": 7,
            "apiUrl": "ha0qqhw2Hs",
            "repeaterRssi": -82,
            "supportedCommunicationIntervals": "EIrtx4fjP0",
            "batteryLevel": 36.475,
            "longitude": 165.6722894337356,
            "on": true,
            "communicationInterval": 8868,
            "rssi": -29.3,
            "batteryVoltage": 20.6,
            "powerUsage": 2305.2,
            "declaredMaximumPower": 1275.1,
            "hob3HeatLevelRemaining": 49,
            "voltage": 368458.553,
            "connectionStatus": false,
            "gatewayIdentifier": "p84YlycX8R",
            "hob1HeatLevelRemaining": 89,
            "hob4HeatLevelRemaining": 49,
            "configuredLocationName": "p6SdSyVbhx",
            "hob2HeatLevelSetting": 50
        },
        {
            "pushButtonState": false,
            "hob3HeatLevelSetting": 0,
            "standby": true,
            "latitude": -13.01686410296628,
            "batteryChargingState": false,
            "lockBit": false,
            "powerUsageEstimate": 393.3,
            "deviceStatus": "Driver Stopped",
            "hob2HeatLevelRemaining": 2,
            "apiUrl": "jbG8UFgreI",
            "hob4HeatLevelSetting": 20,
            "repeaterRssi": -85.3,
            "supportedCommunicationIntervals": "r7vYoZpZ0z",
            "batteryLevel": 18.254,
            "longitude": -44.715081723203014,
            "on": true,
            "communicationInterval": 9697,
            "rssi": -111.5,
            "batteryVoltage": 8.28,
            "powerUsage": 1925,
            "declaredMaximumPower": 299.9,
            "hob3HeatLevelRemaining": 19,
            "voltage": 273414.639,
            "connectionStatus": false,
            "gatewayIdentifier": "wnmW5S6PLg",
            "hob1HeatLevelRemaining": 26,
            "hob4HeatLevelRemaining": 89,
            "configuredLocationName": "PTkyRyJSZ4",
            "hob2HeatLevelSetting": 0
        }
    ],
    "examples": [
        {
            "pushButtonState": true,
            "hob3HeatLevelSetting": 90,
            "standby": false,
            "latitude": -62.02728862085637,
            "batteryChargingState": true,
            "lockBit": true,
            "powerUsageEstimate": 3558.5,
            "deviceStatus": "Driver Not Ready",
            "hob1HeatLevelSetting": 50,
            "hob2HeatLevelRemaining": 79,
            "apiUrl": "GTVA6orVf0",
            "hob4HeatLevelSetting": 10,
            "repeaterRssi": -52.7,
            "supportedCommunicationIntervals": "KZZ0AOUQDJ",
            "batteryLevel": 79.113,
            "longitude": 31.63486925592528,
            "on": false,
            "communicationInterval": 81910,
            "rssi": -81.2,
            "batteryVoltage": 6.77,
            "powerUsage": 1424.2,
            "declaredMaximumPower": 1846,
            "hob3HeatLevelRemaining": 61,
            "voltage": 808146.552,
            "connectionStatus": true,
            "gatewayIdentifier": "DHUd7W4PaW",
            "hob1HeatLevelRemaining": 96,
            "hob4HeatLevelRemaining": 34,
            "configuredLocationName": "tFCGnjoaMf",
            "hob2HeatLevelSetting": 10
        },
        {
            "pushButtonState": false,
            "hob3HeatLevelSetting": 30,
            "standby": false,
            "latitude": -60.35088777445061,
            "batteryChargingState": false,
            "lockBit": true,
            "powerUsageEstimate": 3230.3,
            "deviceStatus": "OK",
            "hob1HeatLevelSetting": 80,
            "hob2HeatLevelRemaining": 61,
            "apiUrl": "TgZvtwMTPV",
            "hob4HeatLevelSetting": 80,
            "repeaterRssi": -122.7,
            "supportedCommunicationIntervals": "ehU3GCNQsy",
            "batteryLevel": 84.813,
            "longitude": -1.5939899053140039,
            "on": false,
            "communicationInterval": 67563,
            "rssi": -1.4,
            "batteryVoltage": 7.85,
            "powerUsage": 2621.8,
            "declaredMaximumPower": 157.8,
            "hob3HeatLevelRemaining": 84,
            "voltage": 372647.685,
            "connectionStatus": false,
            "gatewayIdentifier": "yOYwgb1Sol",
            "hob1HeatLevelRemaining": 84,
            "hob4HeatLevelRemaining": 7,
            "configuredLocationName": "weLUHxzzLS",
            "hob2HeatLevelSetting": 50
        },
        {
            "pushButtonState": false,
            "hob3HeatLevelSetting": 20,
            "standby": true,
            "latitude": 87.39388199255492,
            "batteryChargingState": false,
            "lockBit": false,
            "powerUsageEstimate": 2896.8,
            "deviceStatus": "Driver Stopped",
            "hob1HeatLevelSetting": 40,
            "hob2HeatLevelRemaining": 81,
            "apiUrl": "Jw0yOIiE7t",
            "hob4HeatLevelSetting": 80,
            "repeaterRssi": -23.4,
            "supportedCommunicationIntervals": "rBNnfNF377",
            "batteryLevel": 20.209,
            "longitude": -127.01460486358701,
            "on": true,
            "communicationInterval": 70612,
            "rssi": -119.8,
            "batteryVoltage": 6.28,
            "powerUsage": 3427.4,
            "declaredMaximumPower": 390.8,
            "hob3HeatLevelRemaining": 83,
            "voltage": -334876.772,
            "connectionStatus": false,
            "gatewayIdentifier": "QIwc57tB1Z",
            "hob1HeatLevelRemaining": 52,
            "hob4HeatLevelRemaining": 85,
            "configuredLocationName": "i8xZn8x5Iz",
            "hob2HeatLevelSetting": 40
        },
        {
            "pushButtonState": false,
            "hob3HeatLevelSetting": 90,
            "standby": true,
            "latitude": 49.48877776695184,
            "batteryChargingState": true,
            "lockBit": false,
            "powerUsageEstimate": 324.1,
            "deviceStatus": "OK",
            "hob1HeatLevelSetting": 80,
            "hob2HeatLevelRemaining": 7,
            "apiUrl": "ha0qqhw2Hs",
            "hob4HeatLevelSetting": 60,
            "repeaterRssi": -82,
            "supportedCommunicationIntervals": "EIrtx4fjP0",
            "batteryLevel": 36.475,
            "longitude": 165.6722894337356,
            "on": true,
            "communicationInterval": 8868,
            "rssi": -29.3,
            "batteryVoltage": 20.6,
            "powerUsage": 2305.2,
            "declaredMaximumPower": 1275.1,
            "hob3HeatLevelRemaining": 49,
            "voltage": 368458.553,
            "connectionStatus": false,
            "gatewayIdentifier": "p84YlycX8R",
            "hob1HeatLevelRemaining": 89,
            "hob4HeatLevelRemaining": 49,
            "configuredLocationName": "p6SdSyVbhx",
            "hob2HeatLevelSetting": 50
        },
        {
            "pushButtonState": false,
            "hob3HeatLevelSetting": 0,
            "standby": true,
            "latitude": -13.01686410296628,
            "batteryChargingState": false,
            "lockBit": false,
            "powerUsageEstimate": 393.3,
            "deviceStatus": "Driver Stopped",
            "hob1HeatLevelSetting": 10,
            "hob2HeatLevelRemaining": 2,
            "apiUrl": "jbG8UFgreI",
            "hob4HeatLevelSetting": 20,
            "repeaterRssi": -85.3,
            "supportedCommunicationIntervals": "r7vYoZpZ0z",
            "batteryLevel": 18.254,
            "longitude": -44.715081723203014,
            "on": true,
            "communicationInterval": 9697,
            "rssi": -111.5,
            "batteryVoltage": 8.28,
            "powerUsage": 1925,
            "declaredMaximumPower": 299.9,
            "hob3HeatLevelRemaining": 19,
            "voltage": 273414.639,
            "connectionStatus": false,
            "gatewayIdentifier": "wnmW5S6PLg",
            "hob1HeatLevelRemaining": 26,
            "hob4HeatLevelRemaining": 89,
            "configuredLocationName": "PTkyRyJSZ4",
            "hob2HeatLevelSetting": 0
        }
    ]
}